odoo/addons/license_partner_commission/LICENSE
odoo/addons/license_partner_commission/README.rst
odoo/addons/license_partner_commission/__init__.py
odoo/addons/license_partner_commission/__manifest__.py
odoo/addons/license_partner_commission/images/screen.png
odoo/addons/license_partner_commission/models/__init__.py
odoo/addons/license_partner_commission/models/license_license.py
odoo/addons/license_partner_commission/readme/CONTRIBUTORS.md
odoo/addons/license_partner_commission/readme/DESCRIPTION.md
odoo/addons/license_partner_commission/readme/USAGE.md
odoo/addons/license_partner_commission/static/description/icon.png
odoo/addons/license_partner_commission/static/description/index.html
odoo/addons/license_partner_commission/views/license_license_views.xml
odoo_addon_license_partner_commission-18.0.1.0.0.dist-info/METADATA
odoo_addon_license_partner_commission-18.0.1.0.0.dist-info/WHEEL
odoo_addon_license_partner_commission-18.0.1.0.0.dist-info/top_level.txt
odoo_addon_license_partner_commission-18.0.1.0.0.dist-info/RECORD
